md_llm_lang_reader/__init__.py
md_llm_lang_reader/cli.py
md_llm_lang_reader/generator.py
md_llm_lang_reader-0.2.0.dist-info/licenses/LICENSE.txt
md_llm_lang_reader-0.2.0.dist-info/METADATA
md_llm_lang_reader-0.2.0.dist-info/WHEEL
md_llm_lang_reader-0.2.0.dist-info/entry_points.txt
md_llm_lang_reader-0.2.0.dist-info/top_level.txt
md_llm_lang_reader-0.2.0.dist-info/RECORD
