Metadata-Version: 2.4
Name: md-llm-lang-reader
Version: 0.2.0
Summary: Generate language-learning HTML readers (with sentence-level LLM translations and TTS) from Markdown.
Author: Katsutoshi Seki
License: MIT
Project-URL: Homepage, https://github.com/sekika/langreader/blob/main/README.md
Project-URL: Documentation, https://sekika.github.io/langreader/
Project-URL: Source, https://github.com/sekika/langreader
Classifier: Development Status :: 4 - Beta
Classifier: Intended Audience :: Developers
Classifier: Intended Audience :: Education
Classifier: Intended Audience :: End Users/Desktop
Classifier: License :: OSI Approved :: MIT License
Classifier: Operating System :: OS Independent
Classifier: Programming Language :: Python :: 3
Classifier: Programming Language :: Python :: 3.8
Classifier: Programming Language :: Python :: 3.9
Classifier: Programming Language :: Python :: 3.10
Classifier: Programming Language :: Python :: 3.11
Classifier: Programming Language :: Python :: 3.12
Classifier: Programming Language :: Python :: 3.13
Classifier: Topic :: Education
Classifier: Topic :: Education :: Computer Aided Instruction (CAI)
Classifier: Topic :: Scientific/Engineering :: Artificial Intelligence
Classifier: Topic :: Text Processing :: Markup :: HTML
Classifier: Topic :: Text Processing :: Markup :: Markdown
Classifier: Topic :: Utilities
Classifier: Environment :: Console
Requires-Python: >=3.9
License-File: LICENSE.txt
Requires-Dist: multiai
Dynamic: license-file
